[
  {
    "id": 1,
    "address": "​Россия, Санкт-Петербург, улица Шувалова, 11",
    "geo": [
      60.056786,
      30.427547
    ],
    "img": "/statics/logo.png",
    "time": "С 10:00 до 22:00"
  },
  {
    "id": 2,
    "address": "Россия, Санкт-Петербург, ​​Большая Разночинная улица, 25а",
    "geo": [
      59.961489,
      30.286897
    ],
    "img": "/statics/logo.png",
    "time": "С 10:00 до 22:00"
  },
  {
    "id": 3,
    "address": "​​Россия, Санкт-Петербург, Софийская улица, 14",
    "geo": [
      59.88115,
      30.39757
    ],
    "img": "/statics/logo.png",
    "time": "С 10:00 до 22:00"
  }
]